py_key/__init__.py
py_key/key_config.py
py_key-0.0.2.dist-info/METADATA
py_key-0.0.2.dist-info/WHEEL
py_key-0.0.2.dist-info/top_level.txt
py_key-0.0.2.dist-info/RECORD
